{
    "host": "http://localhost",
    "port": 3000,
    "siteName": "Talk Dater",
    "ooth": {
        "sessionSecret": "somesecret",
        "sharedSecret": "somesharedsecret",
        "path": "/auth"
    },
    "mongo": {
        "url": "mongodb://localhost:27017",
        "db": "talkdater",
        "user": "admin",
        "pwd": "nimda"
    },
    "mail": {
        "nodemailer": {
            "host": "smtp.googlemail.com", // smtp server
            "port": 465, // smtp server port
            "secure": true, // true for 465, false for other ports
            "auth": {
                "user": "abc@def.gh", // user account
                "pass": "supersecurepassword", // password of user    
            }       
        },
        "from": "abc@def.gh", // sender email address
        "urls": {
            "verifyEmail": "/local/verify?token={verification-token}&userId={user-id}",
            "resetPassword": "/reset-password?token={password-reset-token}&userId={user-id}"
        }
    }  
}